plone.app.widgets-5.0.2-py3.13-nspkg.pth
plone/app/widgets/__init__.py
plone/app/widgets/base.py
plone/app/widgets/configure.zcml
plone/app/widgets/factories.py
plone/app/widgets/interfaces.py
plone/app/widgets/testing.py
plone/app/widgets/utils.py
plone/app/widgets/tests/__init__.py
plone/app/widgets/tests/configure.zcml
plone/app/widgets/tests/test_base.py
plone/app/widgets/tests/test_robot.py
plone/app/widgets/tests/test_utils.py
plone/app/widgets/tests/robot/__init__.py
plone/app/widgets/tests/robot/common.robot
plone/app/widgets/tests/robot/deactivate_test_querystring_widget.robot
plone/app/widgets/tests/robot/deactivate_test_select_widget.robot
plone.app.widgets-5.0.2.dist-info/LICENSE.GPL
plone.app.widgets-5.0.2.dist-info/LICENSE.txt
plone.app.widgets-5.0.2.dist-info/METADATA
plone.app.widgets-5.0.2.dist-info/WHEEL
plone.app.widgets-5.0.2.dist-info/namespace_packages.txt
plone.app.widgets-5.0.2.dist-info/top_level.txt
plone.app.widgets-5.0.2.dist-info/RECORD
