Metadata-Version: 2.1
Name: plone.app.widgets
Version: 5.0.2
Summary: better plone widgets
Home-page: https://github.com/plone/plone.app.widgets
Author: Nathan Van Gheem
Author-email: vangheem@gmail.com
License: GPL
Keywords: plone widgets z3cform
Classifier: Development Status :: 5 - Production/Stable
Classifier: Framework :: Plone
Classifier: Framework :: Plone :: 6.0
Classifier: Framework :: Plone :: Core
Classifier: License :: OSI Approved :: GNU General Public License (GPL)
Classifier: Programming Language :: Python
Classifier: Programming Language :: Python :: 3.8
Classifier: Programming Language :: Python :: 3.9
Classifier: Programming Language :: Python :: 3.10
Classifier: Programming Language :: Python :: 3.11
Requires-Python: >=3.8
License-File: LICENSE.GPL
License-File: LICENSE.txt
Requires-Dist: setuptools
Requires-Dist: plone.app.vocabularies>=2.1.12
Requires-Dist: plone.base
Requires-Dist: six
Provides-Extra: test
Requires-Dist: plone.app.robotframework[debug]; extra == "test"
Requires-Dist: plone.app.testing>=4.2.4; extra == "test"
Requires-Dist: mock; extra == "test"
Provides-Extra: dexterity
Requires-Dist: pytz; extra == "dexterity"
Requires-Dist: plone.app.dexterity; extra == "dexterity"
Requires-Dist: plone.app.contenttypes>=1.1; extra == "dexterity"
Requires-Dist: plone.app.event>=1.2; extra == "dexterity"
